{
	"info": {
		"_postman_id": "e3ae221d-a379-4ede-9609-94ef03da7fd2",
		"name": "cars_api",
		"schema": "https://schema.getpostman.com/json/collection/v2.1.0/collection.json",
		"_exporter_id": "21314921"
	},
	"item": [
		{
			"name": "get_all_cars",
			"request": {
				"method": "GET",
				"header": []
			},
			"response": []
		},
		{
			"name": "create_car",
			"request": {
				"method": "POST",
				"header": [],
				"body": {
					"mode": "raw",
					"raw": "{\r\n    \"make: \"Ford\",\r\n    \"model\": \"Fusion\",\r\n    \"year\": 2017,\r\n    \"price\": 25000.0\r\n}",
					"options": {
						"raw": {
							"language": "json"
						}
					}
				},
				"url": {
					"raw": "127.0.0.1:8000/api/cars",
					"host": [
						"127",
						"0",
						"0",
						"1"
					],
					"port": "8000",
					"path": [
						"api",
						"cars"
					]
				}
			},
			"response": []
		},
		{
			"name": "get_car_id",
			"request": {
				"method": "GET",
				"header": [],
				"url": {
					"raw": "127.0.0.1:8000/api/cars/1/",
					"host": [
						"127",
						"0",
						"0",
						"1"
					],
					"port": "8000",
					"path": [
						"api",
						"cars",
						"1",
						""
					]
				}
			},
			"response": []
		},
		{
			"name": "Get_Car_By_Id",
			"request": {
				"method": "GET",
				"header": [],
				"url": {
					"raw": "127.0.0.1:8000/api/cars/3/",
					"host": [
						"127",
						"0",
						"0",
						"1"
					],
					"port": "8000",
					"path": [
						"api",
						"cars",
						"3",
						""
					]
				}
			},
			"response": []
		},
		{
			"name": "Update_Car",
			"request": {
				"method": "PUT",
				"header": [],
				"body": {
					"mode": "raw",
					"raw": "{\r\n    \"make\": \"Ford\",\r\n    \"model\": \"Fusion\",\r\n    \"year\": 2017,\r\n    \"price\": 25000.0\r\n}",
					"options": {
						"raw": {
							"language": "json"
						}
					}
				},
				"url": {
					"raw": "127.0.0.1:8000/api/cars/3/",
					"host": [
						"127",
						"0",
						"0",
						"1"
					],
					"port": "8000",
					"path": [
						"api",
						"cars",
						"3",
						""
					]
				}
			},
			"response": []
		},
		{
			"name": "Delete_Car",
			"request": {
				"method": "GET",
				"header": []
			},
			"response": []
		}
	]
}